oslo_log/__init__.py
oslo_log/_i18n.py
oslo_log/_options.py
oslo_log/formatters.py
oslo_log/handlers.py
oslo_log/helpers.py
oslo_log/log.py
oslo_log/pipe_mutex.py
oslo_log/py.typed
oslo_log/rate_limit.py
oslo_log/version.py
oslo_log/versionutils.py
oslo_log/cmds/__init__.py
oslo_log/cmds/convert_json.py
oslo_log/fixture/__init__.py
oslo_log/fixture/logging_error.py
oslo_log/fixture/setlevel.py
oslo_log/locale/de/LC_MESSAGES/oslo_log.po
oslo_log/locale/en_GB/LC_MESSAGES/oslo_log.po
oslo_log/locale/es/LC_MESSAGES/oslo_log.po
oslo_log/locale/ja/LC_MESSAGES/oslo_log.po
oslo_log/tests/__init__.py
oslo_log/tests/unit/__init__.py
oslo_log/tests/unit/test_convert_json.py
oslo_log/tests/unit/test_custom_loghandler.py
oslo_log/tests/unit/test_formatters.py
oslo_log/tests/unit/test_helpers.py
oslo_log/tests/unit/test_log.py
oslo_log/tests/unit/test_pipe_mutex.py
oslo_log/tests/unit/test_rate_limit.py
oslo_log/tests/unit/test_versionutils.py
oslo_log/tests/unit/fixture/__init__.py
oslo_log/tests/unit/fixture/test_logging_error.py
oslo_log/tests/unit/fixture/test_setlevel.py
oslo_log-8.0.0.dist-info/licenses/AUTHORS
oslo_log-8.0.0.dist-info/licenses/LICENSE
oslo_log-8.0.0.dist-info/METADATA
oslo_log-8.0.0.dist-info/WHEEL
oslo_log-8.0.0.dist-info/entry_points.txt
oslo_log-8.0.0.dist-info/pbr.json
oslo_log-8.0.0.dist-info/top_level.txt
oslo_log-8.0.0.dist-info/RECORD
