Metadata-Version: 2.4
Name: oslo.log
Version: 8.0.0
Summary: oslo.log library
Author-email: OpenStack <openstack-discuss@lists.openstack.org>
Project-URL: Homepage, https://docs.openstack.org/oslo.log
Project-URL: Repository, https://opendev.org/openstack/oslo.log
Classifier: Environment :: OpenStack
Classifier: Intended Audience :: Information Technology
Classifier: Intended Audience :: System Administrators
Classifier: License :: OSI Approved :: Apache Software License
Classifier: Operating System :: POSIX :: Linux
Classifier: Programming Language :: Python
Classifier: Programming Language :: Python :: 3
Classifier: Programming Language :: Python :: 3.10
Classifier: Programming Language :: Python :: 3.11
Classifier: Programming Language :: Python :: 3.12
Classifier: Programming Language :: Python :: 3.13
Classifier: Programming Language :: Python :: 3 :: Only
Classifier: Programming Language :: Python :: Implementation :: CPython
Requires-Python: >=3.10
License-File: LICENSE
Requires-Dist: pbr>=3.1.1
Requires-Dist: oslo.config>=5.2.0
Requires-Dist: oslo.context>=2.21.0
Requires-Dist: oslo.i18n>=3.20.0
Requires-Dist: oslo.utils>=3.36.0
Requires-Dist: oslo.serialization>=2.25.0
Requires-Dist: python-dateutil>=2.7.0
Requires-Dist: debtcollector>=3.0.0
Provides-Extra: fixtures
Requires-Dist: fixtures>=3.0.0; extra == "fixtures"
Provides-Extra: systemd
Requires-Dist: systemd-python>=234; extra == "systemd"
Dynamic: license-file
Dynamic: requires-dist
